<?xml version="1.0" encoding="utf-8"?>
<!DOCTYPE hibernate-mapping PUBLIC "-//Hibernate/Hibernate Mapping DTD 3.0//EN"
"http://hibernate.sourceforge.net/hibernate-mapping-3.0.dtd">
<!-- 
    Mapping file autogenerated by MyEclipse Persistence Tools
-->
<hibernate-mapping>
    <class name="com.sgepit.frame.xgridTemplet.hbm.SgprjTempletConfig" table="SGPRJ_TEMPLET_CONFIG">
        <id name="templetSn" type="java.lang.String">
            <column name="TEMPLET_SN" length="60" />
            <generator class="com.sgepit.frame.util.UUIDGenerator" />
        </id>
        <property name="templetType" type="java.lang.String">
            <column name="TEMPLET_TYPE" length="20" />
        </property>
        <property name="sjType" type="java.lang.String">
            <column name="SJ_TYPE" length="10" />
        </property>
        <property name="unitId" type="java.lang.String">
            <column name="UNIT_ID" length="60" />
        </property>
        <property name="category" type="java.lang.String">
            <column name="CATEGORY" length="60" />
        </property>
        <property name="templetFile" type="java.lang.String" update= "false">
            <column name="TEMPLET_FILE" length="60" />
        </property>
        <property name="templetHeader" type="java.lang.String" update= "false">
            <column name="TEMPLET_HEADER" length="0" />
        </property>
        <property name="templetBegancell" type="java.lang.String" update= "false">
            <column name="TEMPLET_BEGANCELL" length="10" />
        </property>
        <property name="note" type="java.lang.String">
            <column name="NOTE" length="200" />
        </property>
    </class>
</hibernate-mapping>
