<?xml version="1.0" encoding="utf-8"?>
<!DOCTYPE hibernate-mapping PUBLIC "-//Hibernate/Hibernate Mapping DTD 3.0//EN"
"http://hibernate.sourceforge.net/hibernate-mapping-3.0.dtd">
<!-- 
    Mapping file autogenerated by MyEclipse Persistence Tools
-->
<hibernate-mapping>
    <class name="com.sgepit.pmis.equipment.hbm.EquStoreinBackView" table="EQU_STOREIN_BACK_VIEW" >
        <id name="uids" type="java.lang.String">
            <column name="UIDS" length="32" />
            <generator class="uuid" />
        </id>
        <property name="conno" type="java.lang.String">
            <column name="CONNO" length="32" />
        </property>
        <property name="conmoneyno" type="java.lang.String">
            <column name="CONMONEYNO" length="32" />
        </property>
        <property name="warehouseNo" type="java.lang.String">
            <column name="WAREHOUSE_NO" length="32" />
        </property>
        <property name="warehouseDate" type="date">
            <column name="WAREHOUSE_DATE" length="7" />
        </property>
        <property name="partyb" type="java.lang.String">
           <column name="PARTYB" length="200"/>
        </property>
        <property name="invoiceno" type="java.lang.String">
           <column name="INVOICENO" length="200"/>
        </property>
        <property name="waretype" type="java.lang.String">
           <column name="WARETYPE" length="100"/>
        </property>
        <property name="wareno" type="java.lang.String">
           <column name="WARENO" length="100"/>
        </property>
        <property name="warehouseInType" type="java.lang.String">
           <column name="WAREHOUSE_IN_TYPE" length="100"/>
        </property>
    </class>
</hibernate-mapping>
