<?xml version="1.0" encoding="utf-8"?>
<!DOCTYPE hibernate-mapping PUBLIC "-//Hibernate/Hibernate Mapping DTD 3.0//EN"
"http://hibernate.sourceforge.net/hibernate-mapping-3.0.dtd">
<!-- 
    Mapping file autogenerated by MyEclipse Persistence Tools
-->
<hibernate-mapping>
    <class name="com.sgepit.pcmis.aqgk.hbm.PcAqgkFeedbackInfo" table="PC_AQGK_FEEDBACK_INFO">
        <id name="uids" type="java.lang.String">
            <column name="UIDS" length="32" />
            <generator class="uuid" />
        </id>
        <property name="pid" type="java.lang.String">
            <column name="PID" length="32" not-null="true">
                <comment>工程项目编号</comment>
            </column>
        </property>
        <property name="feedbackType" type="java.lang.String">
            <column name="FEEDBACK_TYPE" length="100">
                <comment>反馈人所在的单位（公司层面的）</comment>
            </column>
        </property>
        <property name="feedtime" type="java.util.Date">
            <column name="FEEDTIME" length="7">
                <comment>反馈时间</comment>
            </column>
        </property>
        <property name="feedperson" type="java.lang.String">
            <column name="FEEDPERSON" length="50">
                <comment>反馈人</comment>
            </column>
        </property>
        <property name="feedcontent" type="java.lang.String">
            <column name="FEEDCONTENT" length="2000">
                <comment>反馈内容</comment>
            </column>
        </property>
        <property name="infoId" type="java.lang.String">
            <column name="INFO_ID" length="32">
                <comment>反馈意见对应的记录</comment>
            </column>
        </property>
    </class>
</hibernate-mapping>
