<?xml version="1.0" encoding="utf-8"?>
<!DOCTYPE hibernate-mapping PUBLIC "-//Hibernate/Hibernate Mapping DTD 3.0//EN"
"http://hibernate.sourceforge.net/hibernate-mapping-3.0.dtd">
<!-- 
    Mapping file autogenerated by MyEclipse Persistence Tools
-->
<hibernate-mapping>
    <class name="com.sgepit.pmis.finalAccounts.financialAudit.hbm.FaMatAuditReport" table="FA_MAT_AUDIT_REPORT">
        <id name="uids" type="java.lang.String">
            <column name="UIDS" length="100" />
            <generator class="assigned" />
        </id>
        <property name="pid" type="java.lang.String">
            <column name="PID" length="100" not-null="true" />
        </property>
        <property name="assetsNo" type="java.lang.String">
            <column name="ASSETS_NO" length="100" />
        </property>
        <property name="matId" type="java.lang.String">
            <column name="MAT_ID" length="100" not-null="true" />
        </property>
        <property name="auditId" type="java.lang.String">
            <column name="AUDIT_ID" length="100" />
        </property>
        <property name="matName" type="java.lang.String">
            <column name="MAT_NAME" length="100" />
        </property>
        <property name="matSpec" type="java.lang.String">
            <column name="MAT_SPEC" length="200" />
        </property>
        <property name="matSupplyunit" type="java.lang.String">
            <column name="MAT_SUPPLYUNIT" length="200" />
        </property>
        <property name="unit" type="java.lang.String">
            <column name="UNIT" length="200" />
        </property>
        <property name="numA" type="java.math.BigDecimal">
            <column name="NUM_A" precision="18" scale="5" />
        </property>
        <property name="amountA" type="java.math.BigDecimal">
            <column name="AMOUNT_A" precision="18" scale="5" />
        </property>
        <property name="numF" type="java.math.BigDecimal">
            <column name="NUM_F" precision="18" scale="5" />
        </property>
        <property name="amountF" type="java.math.BigDecimal">
            <column name="AMOUNT_F" precision="18" scale="5" />
        </property>
        <property name="matUser" type="java.lang.String">
            <column name="MAT_USER" length="2000" />
        </property>
        <property name="finOAmount" type="java.math.BigDecimal">
            <column name="F_O_AMOUNT" precision="18" scale="5" />
        </property>
        <property name="finDepAmount" type="java.math.BigDecimal">
            <column name="F_DEP_AMOUNT" precision="18" scale="5" />
        </property>
        <property name="finFixedAmount" type="java.math.BigDecimal">
            <column name="F_FIXED_AMOUNT" precision="18" scale="5" />
        </property>
        <property name="finCurrentAmount" type="java.math.BigDecimal">
            <column name="F_CURRENT_AMOUNT" precision="18" scale="5" />
        </property>
        <property name="remark" type="java.lang.String">
            <column name="REMARK" length="2000" />
        </property>
        <property name="mainFlag" type="java.lang.String">
            <column name="MAINFLAG" length="10" />
        </property>
    </class>
</hibernate-mapping>
